porte/__init__.py
porte/porte.py
porte-0.0.2.dist-info/METADATA
porte-0.0.2.dist-info/WHEEL
porte-0.0.2.dist-info/entry_points.txt
porte-0.0.2.dist-info/top_level.txt
porte-0.0.2.dist-info/RECORD
